thoughtwrapper-0.3.0.dist-info/METADATA
thoughtwrapper-0.3.0.dist-info/WHEEL
thoughtwrapper-0.3.0.dist-info/licenses/LICENSE.txt
thoughtwrapper/__init__.py
thoughtwrapper/_devserver.py
thoughtwrapper/_pipeline.py
thoughtwrapper/_site.py
thoughtwrapper/_source.py
thoughtwrapper/_util.py
thoughtwrapper/extras/__init__.py
thoughtwrapper/extras/frontmatter.py
thoughtwrapper/extras/md.py
thoughtwrapper/extras/metadata.py
thoughtwrapper/extras/syntax.py
thoughtwrapper/extras/template.py
thoughtwrapper-0.3.0.dist-info/RECORD
