Metadata-Version: 2.1
Name: thoughtwrapper
Version: 0.3.0
Summary: A Static Site Generator for Tinkerers
Author-Email: Lucas Hinderberger <mail@lucas-hinderberger.de>
License: Apache-2.0
Requires-Python: >=3.12
Requires-Dist: beautifulsoup4>=4.12.3
Requires-Dist: marko>=2.1.2; extra == "md"
Requires-Dist: Pygments>=2.18.0; extra == "syntax"
Requires-Dist: Jinja2>=3.1.4; extra == "template"
Provides-Extra: md
Provides-Extra: syntax
Provides-Extra: template
